[
  {
    "keyword": "Feature",
    "name": "Google Search",
    "line": 1,
    "id": "google-search",
    "tags": [],
    "uri": "features\\google.feature",
    "elements": [
      {
        "id": "google-search;searching-google",
        "keyword": "Scenario",
        "line": 3,
        "name": "Searching Google",
        "tags": [],
        "type": "scenario",
        "steps": [
          {
            "arguments": [],
            "keyword": "Given ",
            "line": 5,
            "name": "I open Google's search page",
            "match": {
              "location": "step-definitions\\google.js:4"
            },
            "result": {
              "status": "passed",
              "duration": 4149000000
            }
          },
          {
            "arguments": [],
            "keyword": "Then ",
            "line": 6,
            "name": "the title is \"Google\"",
            "match": {
              "location": "step-definitions\\google.js:8"
            },
            "result": {
              "status": "passed",
              "duration": 9000000
            }
          },
          {
            "arguments": [],
            "keyword": "And ",
            "line": 7,
            "name": "the Google search form exists",
            "match": {
              "location": "step-definitions\\google.js:12"
            },
            "result": {
              "status": "passed",
              "duration": 33000000
            }
          },
          {
            "keyword": "After",
            "hidden": true,
            "match": {
              "location": "cucumber.conf.js:38"
            },
            "result": {
              "status": "passed",
              "duration": 0
            }
          }
        ]
      }
    ]
  }
]